{
  "version": "tree-0.1",
  "tree": {
    "id": "App",
    "path": "",
    "children": {
      "WorkflowStack": {
        "id": "WorkflowStack",
        "path": "WorkflowStack",
        "children": {
          "AppGreeting": {
            "id": "AppGreeting",
            "path": "WorkflowStack/AppGreeting",
            "children": {
              "Resource": {
                "id": "Resource",
                "path": "WorkflowStack/AppGreeting/Resource",
                "attributes": {
                  "aws:cdk:cloudformation:type": "AWS::SSM::Parameter",
                  "aws:cdk:cloudformation:props": {
                    "description": "Greeting message retrieved dynamically by Lambda at runtime",
                    "name": "/app/config/greeting",
                    "type": "String",
                    "value": "Hello from CI/CD Automated Infrastructure! - Capstone 4"
                  }
                },
                "constructInfo": {
                  "fqn": "aws-cdk-lib.aws_ssm.CfnParameter",
                  "version": "2.100.0"
                }
              }
            },
            "constructInfo": {
              "fqn": "aws-cdk-lib.aws_ssm.StringParameter",
              "version": "2.100.0"
            }
          },
          "LambdaExecutionRole": {
            "id": "LambdaExecutionRole",
            "path": "WorkflowStack/LambdaExecutionRole",
            "children": {
              "ImportLambdaExecutionRole": {
                "id": "ImportLambdaExecutionRole",
                "path": "WorkflowStack/LambdaExecutionRole/ImportLambdaExecutionRole",
                "constructInfo": {
                  "fqn": "aws-cdk-lib.Resource",
                  "version": "2.100.0"
                }
              },
              "Resource": {
                "id": "Resource",
                "path": "WorkflowStack/LambdaExecutionRole/Resource",
                "attributes": {
                  "aws:cdk:cloudformation:type": "AWS::IAM::Role",
                  "aws:cdk:cloudformation:props": {
                    "assumeRolePolicyDocument": {
                      "Statement": [
                        {
                          "Action": "sts:AssumeRole",
                          "Effect": "Allow",
                          "Principal": {
                            "Service": "lambda.amazonaws.com"
                          }
                        }
                      ],
                      "Version": "2012-10-17"
                    },
                    "managedPolicyArns": [
                      {
                        "Fn::Join": [
                          "",
                          [
                            "arn:",
                            {
                              "Ref": "AWS::Partition"
                            },
                            ":iam::aws:policy/service-role/AWSLambdaBasicExecutionRole"
                          ]
                        ]
                      }
                    ]
                  }
                },
                "constructInfo": {
                  "fqn": "aws-cdk-lib.aws_iam.CfnRole",
                  "version": "2.100.0"
                }
              },
              "DefaultPolicy": {
                "id": "DefaultPolicy",
                "path": "WorkflowStack/LambdaExecutionRole/DefaultPolicy",
                "children": {
                  "Resource": {
                    "id": "Resource",
                    "path": "WorkflowStack/LambdaExecutionRole/DefaultPolicy/Resource",
                    "attributes": {
                      "aws:cdk:cloudformation:type": "AWS::IAM::Policy",
                      "aws:cdk:cloudformation:props": {
                        "policyDocument": {
                          "Statement": [
                            {
                              "Action": [
                                "ssm:DescribeParameters",
                                "ssm:GetParameter",
                                "ssm:GetParameterHistory",
                                "ssm:GetParameters"
                              ],
                              "Effect": "Allow",
                              "Resource": {
                                "Fn::Join": [
                                  "",
                                  [
                                    "arn:",
                                    {
                                      "Ref": "AWS::Partition"
                                    },
                                    ":ssm:us-east-1:132831332261:parameter",
                                    {
                                      "Ref": "AppGreeting4455FE37"
                                    }
                                  ]
                                ]
                              }
                            }
                          ],
                          "Version": "2012-10-17"
                        },
                        "policyName": "LambdaExecutionRoleDefaultPolicy6D69732F",
                        "roles": [
                          {
                            "Ref": "LambdaExecutionRoleD5C26073"
                          }
                        ]
                      }
                    },
                    "constructInfo": {
                      "fqn": "aws-cdk-lib.aws_iam.CfnPolicy",
                      "version": "2.100.0"
                    }
                  }
                },
                "constructInfo": {
                  "fqn": "aws-cdk-lib.aws_iam.Policy",
                  "version": "2.100.0"
                }
              }
            },
            "constructInfo": {
              "fqn": "aws-cdk-lib.aws_iam.Role",
              "version": "2.100.0"
            }
          },
          "WorkflowTask": {
            "id": "WorkflowTask",
            "path": "WorkflowStack/WorkflowTask",
            "children": {
              "Code": {
                "id": "Code",
                "path": "WorkflowStack/WorkflowTask/Code",
                "children": {
                  "Stage": {
                    "id": "Stage",
                    "path": "WorkflowStack/WorkflowTask/Code/Stage",
                    "constructInfo": {
                      "fqn": "aws-cdk-lib.AssetStaging",
                      "version": "2.100.0"
                    }
                  },
                  "AssetBucket": {
                    "id": "AssetBucket",
                    "path": "WorkflowStack/WorkflowTask/Code/AssetBucket",
                    "constructInfo": {
                      "fqn": "aws-cdk-lib.aws_s3.BucketBase",
                      "version": "2.100.0"
                    }
                  }
                },
                "constructInfo": {
                  "fqn": "aws-cdk-lib.aws_s3_assets.Asset",
                  "version": "2.100.0"
                }
              },
              "Resource": {
                "id": "Resource",
                "path": "WorkflowStack/WorkflowTask/Resource",
                "attributes": {
                  "aws:cdk:cloudformation:type": "AWS::Lambda::Function",
                  "aws:cdk:cloudformation:props": {
                    "code": {
                      "s3Bucket": "cdk-hnb659fds-assets-132831332261-us-east-1",
                      "s3Key": "a4e4dff393f25d8f32337a833bcc561d6e5688c57a84e22f1ec746f85ecc3832.zip"
                    },
                    "environment": {
                      "variables": {
                        "SSM_PARAM_NAME": "/app/config/greeting"
                      }
                    },
                    "handler": "index.handler",
                    "role": {
                      "Fn::GetAtt": [
                        "LambdaExecutionRoleD5C26073",
                        "Arn"
                      ]
                    },
                    "runtime": "nodejs18.x",
                    "timeout": 30
                  }
                },
                "constructInfo": {
                  "fqn": "aws-cdk-lib.aws_lambda.CfnFunction",
                  "version": "2.100.0"
                }
              },
              "LogRetention": {
                "id": "LogRetention",
                "path": "WorkflowStack/WorkflowTask/LogRetention",
                "children": {
                  "Resource": {
                    "id": "Resource",
                    "path": "WorkflowStack/WorkflowTask/LogRetention/Resource",
                    "constructInfo": {
                      "fqn": "aws-cdk-lib.CfnResource",
                      "version": "2.100.0"
                    }
                  }
                },
                "constructInfo": {
                  "fqn": "aws-cdk-lib.aws_logs.LogRetention",
                  "version": "2.100.0"
                }
              },
              "LogGroup": {
                "id": "LogGroup",
                "path": "WorkflowStack/WorkflowTask/LogGroup",
                "constructInfo": {
                  "fqn": "aws-cdk-lib.Resource",
                  "version": "2.100.0"
                }
              }
            },
            "constructInfo": {
              "fqn": "aws-cdk-lib.aws_lambda.Function",
              "version": "2.100.0"
            }
          },
          "LogRetentionaae0aa3c5b4d4f87b02d85b201efdd8a": {
            "id": "LogRetentionaae0aa3c5b4d4f87b02d85b201efdd8a",
            "path": "WorkflowStack/LogRetentionaae0aa3c5b4d4f87b02d85b201efdd8a",
            "children": {
              "Code": {
                "id": "Code",
                "path": "WorkflowStack/LogRetentionaae0aa3c5b4d4f87b02d85b201efdd8a/Code",
                "children": {
                  "Stage": {
                    "id": "Stage",
                    "path": "WorkflowStack/LogRetentionaae0aa3c5b4d4f87b02d85b201efdd8a/Code/Stage",
                    "constructInfo": {
                      "fqn": "aws-cdk-lib.AssetStaging",
                      "version": "2.100.0"
                    }
                  },
                  "AssetBucket": {
                    "id": "AssetBucket",
                    "path": "WorkflowStack/LogRetentionaae0aa3c5b4d4f87b02d85b201efdd8a/Code/AssetBucket",
                    "constructInfo": {
                      "fqn": "aws-cdk-lib.aws_s3.BucketBase",
                      "version": "2.100.0"
                    }
                  }
                },
                "constructInfo": {
                  "fqn": "aws-cdk-lib.aws_s3_assets.Asset",
                  "version": "2.100.0"
                }
              },
              "ServiceRole": {
                "id": "ServiceRole",
                "path": "WorkflowStack/LogRetentionaae0aa3c5b4d4f87b02d85b201efdd8a/ServiceRole",
                "children": {
                  "ImportServiceRole": {
                    "id": "ImportServiceRole",
                    "path": "WorkflowStack/LogRetentionaae0aa3c5b4d4f87b02d85b201efdd8a/ServiceRole/ImportServiceRole",
                    "constructInfo": {
                      "fqn": "aws-cdk-lib.Resource",
                      "version": "2.100.0"
                    }
                  },
                  "Resource": {
                    "id": "Resource",
                    "path": "WorkflowStack/LogRetentionaae0aa3c5b4d4f87b02d85b201efdd8a/ServiceRole/Resource",
                    "attributes": {
                      "aws:cdk:cloudformation:type": "AWS::IAM::Role",
                      "aws:cdk:cloudformation:props": {
                        "assumeRolePolicyDocument": {
                          "Statement": [
                            {
                              "Action": "sts:AssumeRole",
                              "Effect": "Allow",
                              "Principal": {
                                "Service": "lambda.amazonaws.com"
                              }
                            }
                          ],
                          "Version": "2012-10-17"
                        },
                        "managedPolicyArns": [
                          {
                            "Fn::Join": [
                              "",
                              [
                                "arn:",
                                {
                                  "Ref": "AWS::Partition"
                                },
                                ":iam::aws:policy/service-role/AWSLambdaBasicExecutionRole"
                              ]
                            ]
                          }
                        ]
                      }
                    },
                    "constructInfo": {
                      "fqn": "aws-cdk-lib.aws_iam.CfnRole",
                      "version": "2.100.0"
                    }
                  },
                  "DefaultPolicy": {
                    "id": "DefaultPolicy",
                    "path": "WorkflowStack/LogRetentionaae0aa3c5b4d4f87b02d85b201efdd8a/ServiceRole/DefaultPolicy",
                    "children": {
                      "Resource": {
                        "id": "Resource",
                        "path": "WorkflowStack/LogRetentionaae0aa3c5b4d4f87b02d85b201efdd8a/ServiceRole/DefaultPolicy/Resource",
                        "attributes": {
                          "aws:cdk:cloudformation:type": "AWS::IAM::Policy",
                          "aws:cdk:cloudformation:props": {
                            "policyDocument": {
                              "Statement": [
                                {
                                  "Action": [
                                    "logs:DeleteRetentionPolicy",
                                    "logs:PutRetentionPolicy"
                                  ],
                                  "Effect": "Allow",
                                  "Resource": "*"
                                }
                              ],
                              "Version": "2012-10-17"
                            },
                            "policyName": "LogRetentionaae0aa3c5b4d4f87b02d85b201efdd8aServiceRoleDefaultPolicyADDA7DEB",
                            "roles": [
                              {
                                "Ref": "LogRetentionaae0aa3c5b4d4f87b02d85b201efdd8aServiceRole9741ECFB"
                              }
                            ]
                          }
                        },
                        "constructInfo": {
                          "fqn": "aws-cdk-lib.aws_iam.CfnPolicy",
                          "version": "2.100.0"
                        }
                      }
                    },
                    "constructInfo": {
                      "fqn": "aws-cdk-lib.aws_iam.Policy",
                      "version": "2.100.0"
                    }
                  }
                },
                "constructInfo": {
                  "fqn": "aws-cdk-lib.aws_iam.Role",
                  "version": "2.100.0"
                }
              },
              "Resource": {
                "id": "Resource",
                "path": "WorkflowStack/LogRetentionaae0aa3c5b4d4f87b02d85b201efdd8a/Resource",
                "constructInfo": {
                  "fqn": "aws-cdk-lib.CfnResource",
                  "version": "2.100.0"
                }
              }
            },
            "constructInfo": {
              "fqn": "constructs.Construct",
              "version": "10.6.0"
            }
          },
          "InitializeWorkflow": {
            "id": "InitializeWorkflow",
            "path": "WorkflowStack/InitializeWorkflow",
            "constructInfo": {
              "fqn": "aws-cdk-lib.aws_stepfunctions.Pass",
              "version": "2.100.0"
            }
          },
          "WaitBeforeTask": {
            "id": "WaitBeforeTask",
            "path": "WorkflowStack/WaitBeforeTask",
            "constructInfo": {
              "fqn": "aws-cdk-lib.aws_stepfunctions.Wait",
              "version": "2.100.0"
            }
          },
          "InvokeLambdaTask": {
            "id": "InvokeLambdaTask",
            "path": "WorkflowStack/InvokeLambdaTask",
            "constructInfo": {
              "fqn": "aws-cdk-lib.aws_stepfunctions_tasks.LambdaInvoke",
              "version": "2.100.0"
            }
          },
          "WorkflowFailed": {
            "id": "WorkflowFailed",
            "path": "WorkflowStack/WorkflowFailed",
            "constructInfo": {
              "fqn": "aws-cdk-lib.aws_stepfunctions.Fail",
              "version": "2.100.0"
            }
          },
          "WorkflowSucceeded": {
            "id": "WorkflowSucceeded",
            "path": "WorkflowStack/WorkflowSucceeded",
            "constructInfo": {
              "fqn": "aws-cdk-lib.aws_stepfunctions.Succeed",
              "version": "2.100.0"
            }
          },
          "StateMachineLogs": {
            "id": "StateMachineLogs",
            "path": "WorkflowStack/StateMachineLogs",
            "children": {
              "Resource": {
                "id": "Resource",
                "path": "WorkflowStack/StateMachineLogs/Resource",
                "attributes": {
                  "aws:cdk:cloudformation:type": "AWS::Logs::LogGroup",
                  "aws:cdk:cloudformation:props": {
                    "logGroupName": "/aws/states/workflow-state-machine",
                    "retentionInDays": 7
                  }
                },
                "constructInfo": {
                  "fqn": "aws-cdk-lib.aws_logs.CfnLogGroup",
                  "version": "2.100.0"
                }
              }
            },
            "constructInfo": {
              "fqn": "aws-cdk-lib.aws_logs.LogGroup",
              "version": "2.100.0"
            }
          },
          "WorkflowStateMachine": {
            "id": "WorkflowStateMachine",
            "path": "WorkflowStack/WorkflowStateMachine",
            "children": {
              "Role": {
                "id": "Role",
                "path": "WorkflowStack/WorkflowStateMachine/Role",
                "children": {
                  "ImportRole": {
                    "id": "ImportRole",
                    "path": "WorkflowStack/WorkflowStateMachine/Role/ImportRole",
                    "constructInfo": {
                      "fqn": "aws-cdk-lib.Resource",
                      "version": "2.100.0"
                    }
                  },
                  "Resource": {
                    "id": "Resource",
                    "path": "WorkflowStack/WorkflowStateMachine/Role/Resource",
                    "attributes": {
                      "aws:cdk:cloudformation:type": "AWS::IAM::Role",
                      "aws:cdk:cloudformation:props": {
                        "assumeRolePolicyDocument": {
                          "Statement": [
                            {
                              "Action": "sts:AssumeRole",
                              "Effect": "Allow",
                              "Principal": {
                                "Service": "states.us-east-1.amazonaws.com"
                              }
                            }
                          ],
                          "Version": "2012-10-17"
                        }
                      }
                    },
                    "constructInfo": {
                      "fqn": "aws-cdk-lib.aws_iam.CfnRole",
                      "version": "2.100.0"
                    }
                  },
                  "DefaultPolicy": {
                    "id": "DefaultPolicy",
                    "path": "WorkflowStack/WorkflowStateMachine/Role/DefaultPolicy",
                    "children": {
                      "Resource": {
                        "id": "Resource",
                        "path": "WorkflowStack/WorkflowStateMachine/Role/DefaultPolicy/Resource",
                        "attributes": {
                          "aws:cdk:cloudformation:type": "AWS::IAM::Policy",
                          "aws:cdk:cloudformation:props": {
                            "policyDocument": {
                              "Statement": [
                                {
                                  "Action": [
                                    "logs:CreateLogDelivery",
                                    "logs:DeleteLogDelivery",
                                    "logs:DescribeLogGroups",
                                    "logs:DescribeResourcePolicies",
                                    "logs:GetLogDelivery",
                                    "logs:ListLogDeliveries",
                                    "logs:PutResourcePolicy",
                                    "logs:UpdateLogDelivery",
                                    "xray:GetSamplingRules",
                                    "xray:GetSamplingTargets",
                                    "xray:PutTelemetryRecords",
                                    "xray:PutTraceSegments"
                                  ],
                                  "Effect": "Allow",
                                  "Resource": "*"
                                },
                                {
                                  "Action": "lambda:InvokeFunction",
                                  "Effect": "Allow",
                                  "Resource": [
                                    {
                                      "Fn::GetAtt": [
                                        "WorkflowTask865FF66C",
                                        "Arn"
                                      ]
                                    },
                                    {
                                      "Fn::Join": [
                                        "",
                                        [
                                          {
                                            "Fn::GetAtt": [
                                              "WorkflowTask865FF66C",
                                              "Arn"
                                            ]
                                          },
                                          ":*"
                                        ]
                                      ]
                                    }
                                  ]
                                }
                              ],
                              "Version": "2012-10-17"
                            },
                            "policyName": "WorkflowStateMachineRoleDefaultPolicyDAB74B4D",
                            "roles": [
                              {
                                "Ref": "WorkflowStateMachineRoleE0545793"
                              }
                            ]
                          }
                        },
                        "constructInfo": {
                          "fqn": "aws-cdk-lib.aws_iam.CfnPolicy",
                          "version": "2.100.0"
                        }
                      }
                    },
                    "constructInfo": {
                      "fqn": "aws-cdk-lib.aws_iam.Policy",
                      "version": "2.100.0"
                    }
                  }
                },
                "constructInfo": {
                  "fqn": "aws-cdk-lib.aws_iam.Role",
                  "version": "2.100.0"
                }
              },
              "Resource": {
                "id": "Resource",
                "path": "WorkflowStack/WorkflowStateMachine/Resource",
                "attributes": {
                  "aws:cdk:cloudformation:type": "AWS::StepFunctions::StateMachine",
                  "aws:cdk:cloudformation:props": {
                    "definitionString": {
                      "Fn::Join": [
                        "",
                        [
                          "{\"StartAt\":\"InitializeWorkflow\",\"States\":{\"InitializeWorkflow\":{\"Type\":\"Pass\",\"Comment\":\"Workflow started — initializing context\",\"Result\":{\"workflowStarted\":true,\"message\":\"Proceeding to fetch SSM config via Lambda\"},\"ResultPath\":\"$.init\",\"Next\":\"WaitBeforeTask\"},\"WaitBeforeTask\":{\"Type\":\"Wait\",\"Comment\":\"Simulating a brief wait before invoking Lambda\",\"Seconds\":3,\"Next\":\"InvokeLambdaTask\"},\"InvokeLambdaTask\":{\"Next\":\"WorkflowSucceeded\",\"Retry\":[{\"ErrorEquals\":[\"Lambda.ClientExecutionTimeoutException\",\"Lambda.ServiceException\",\"Lambda.AWSLambdaException\",\"Lambda.SdkClientException\"],\"IntervalSeconds\":2,\"MaxAttempts\":6,\"BackoffRate\":2},{\"ErrorEquals\":[\"States.TaskFailed\",\"Lambda.ServiceException\"],\"IntervalSeconds\":2,\"MaxAttempts\":2,\"BackoffRate\":2}],\"Catch\":[{\"ErrorEquals\":[\"States.ALL\"],\"ResultPath\":\"$.error\",\"Next\":\"WorkflowFailed\"}],\"Type\":\"Task\",\"Comment\":\"Invoke Lambda to retrieve SSM parameter\",\"OutputPath\":\"$.Payload\",\"Resource\":\"arn:",
                          {
                            "Ref": "AWS::Partition"
                          },
                          ":states:::lambda:invoke\",\"Parameters\":{\"FunctionName\":\"",
                          {
                            "Fn::GetAtt": [
                              "WorkflowTask865FF66C",
                              "Arn"
                            ]
                          },
                          "\",\"Payload.$\":\"$\"}},\"WorkflowSucceeded\":{\"Type\":\"Succeed\",\"Comment\":\"Workflow completed successfully\"},\"WorkflowFailed\":{\"Type\":\"Fail\",\"Error\":\"LambdaInvocationError\",\"Cause\":\"Lambda invocation failed after retries\"}},\"TimeoutSeconds\":300}"
                        ]
                      ]
                    },
                    "loggingConfiguration": {
                      "destinations": [
                        {
                          "cloudWatchLogsLogGroup": {
                            "logGroupArn": {
                              "Fn::GetAtt": [
                                "StateMachineLogs3CB16D3C",
                                "Arn"
                              ]
                            }
                          }
                        }
                      ],
                      "includeExecutionData": true,
                      "level": "ALL"
                    },
                    "roleArn": {
                      "Fn::GetAtt": [
                        "WorkflowStateMachineRoleE0545793",
                        "Arn"
                      ]
                    },
                    "stateMachineName": "capstone4-workflow",
                    "tracingConfiguration": {
                      "enabled": true
                    }
                  }
                },
                "constructInfo": {
                  "fqn": "aws-cdk-lib.aws_stepfunctions.CfnStateMachine",
                  "version": "2.100.0"
                }
              }
            },
            "constructInfo": {
              "fqn": "aws-cdk-lib.aws_stepfunctions.StateMachine",
              "version": "2.100.0"
            }
          },
          "LambdaFunctionName": {
            "id": "LambdaFunctionName",
            "path": "WorkflowStack/LambdaFunctionName",
            "constructInfo": {
              "fqn": "aws-cdk-lib.CfnOutput",
              "version": "2.100.0"
            }
          },
          "SSMParameterName": {
            "id": "SSMParameterName",
            "path": "WorkflowStack/SSMParameterName",
            "constructInfo": {
              "fqn": "aws-cdk-lib.CfnOutput",
              "version": "2.100.0"
            }
          },
          "CDKMetadata": {
            "id": "CDKMetadata",
            "path": "WorkflowStack/CDKMetadata",
            "children": {
              "Default": {
                "id": "Default",
                "path": "WorkflowStack/CDKMetadata/Default",
                "constructInfo": {
                  "fqn": "aws-cdk-lib.CfnResource",
                  "version": "2.100.0"
                }
              }
            },
            "constructInfo": {
              "fqn": "constructs.Construct",
              "version": "10.6.0"
            }
          },
          "BootstrapVersion": {
            "id": "BootstrapVersion",
            "path": "WorkflowStack/BootstrapVersion",
            "constructInfo": {
              "fqn": "aws-cdk-lib.CfnParameter",
              "version": "2.100.0"
            }
          },
          "CheckBootstrapVersion": {
            "id": "CheckBootstrapVersion",
            "path": "WorkflowStack/CheckBootstrapVersion",
            "constructInfo": {
              "fqn": "aws-cdk-lib.CfnRule",
              "version": "2.100.0"
            }
          }
        },
        "constructInfo": {
          "fqn": "aws-cdk-lib.Stack",
          "version": "2.100.0"
        }
      },
      "PipelineStack": {
        "id": "PipelineStack",
        "path": "PipelineStack",
        "children": {
          "CdkBuildProject": {
            "id": "CdkBuildProject",
            "path": "PipelineStack/CdkBuildProject",
            "children": {
              "Role": {
                "id": "Role",
                "path": "PipelineStack/CdkBuildProject/Role",
                "children": {
                  "ImportRole": {
                    "id": "ImportRole",
                    "path": "PipelineStack/CdkBuildProject/Role/ImportRole",
                    "constructInfo": {
                      "fqn": "aws-cdk-lib.Resource",
                      "version": "2.100.0"
                    }
                  },
                  "Resource": {
                    "id": "Resource",
                    "path": "PipelineStack/CdkBuildProject/Role/Resource",
                    "attributes": {
                      "aws:cdk:cloudformation:type": "AWS::IAM::Role",
                      "aws:cdk:cloudformation:props": {
                        "assumeRolePolicyDocument": {
                          "Statement": [
                            {
                              "Action": "sts:AssumeRole",
                              "Effect": "Allow",
                              "Principal": {
                                "Service": "codebuild.amazonaws.com"
                              }
                            }
                          ],
                          "Version": "2012-10-17"
                        }
                      }
                    },
                    "constructInfo": {
                      "fqn": "aws-cdk-lib.aws_iam.CfnRole",
                      "version": "2.100.0"
                    }
                  },
                  "DefaultPolicy": {
                    "id": "DefaultPolicy",
                    "path": "PipelineStack/CdkBuildProject/Role/DefaultPolicy",
                    "children": {
                      "Resource": {
                        "id": "Resource",
                        "path": "PipelineStack/CdkBuildProject/Role/DefaultPolicy/Resource",
                        "attributes": {
                          "aws:cdk:cloudformation:type": "AWS::IAM::Policy",
                          "aws:cdk:cloudformation:props": {
                            "policyDocument": {
                              "Statement": [
                                {
                                  "Action": [
                                    "logs:CreateLogGroup",
                                    "logs:CreateLogStream",
                                    "logs:PutLogEvents"
                                  ],
                                  "Effect": "Allow",
                                  "Resource": [
                                    {
                                      "Fn::Join": [
                                        "",
                                        [
                                          "arn:",
                                          {
                                            "Ref": "AWS::Partition"
                                          },
                                          ":logs:us-east-1:132831332261:log-group:/aws/codebuild/",
                                          {
                                            "Ref": "CdkBuildProject9382C38D"
                                          },
                                          ":*"
                                        ]
                                      ]
                                    },
                                    {
                                      "Fn::Join": [
                                        "",
                                        [
                                          "arn:",
                                          {
                                            "Ref": "AWS::Partition"
                                          },
                                          ":logs:us-east-1:132831332261:log-group:/aws/codebuild/",
                                          {
                                            "Ref": "CdkBuildProject9382C38D"
                                          }
                                        ]
                                      ]
                                    }
                                  ]
                                },
                                {
                                  "Action": [
                                    "codebuild:BatchPutCodeCoverages",
                                    "codebuild:BatchPutTestCases",
                                    "codebuild:CreateReport",
                                    "codebuild:CreateReportGroup",
                                    "codebuild:UpdateReport"
                                  ],
                                  "Effect": "Allow",
                                  "Resource": {
                                    "Fn::Join": [
                                      "",
                                      [
                                        "arn:",
                                        {
                                          "Ref": "AWS::Partition"
                                        },
                                        ":codebuild:us-east-1:132831332261:report-group/",
                                        {
                                          "Ref": "CdkBuildProject9382C38D"
                                        },
                                        "-*"
                                      ]
                                    ]
                                  }
                                },
                                {
                                  "Action": [
                                    "cloudformation:*",
                                    "iam:*",
                                    "lambda:*",
                                    "logs:*",
                                    "s3:*",
                                    "ssm:*",
                                    "states:*"
                                  ],
                                  "Effect": "Allow",
                                  "Resource": "*"
                                },
                                {
                                  "Action": [
                                    "s3:Abort*",
                                    "s3:DeleteObject*",
                                    "s3:GetBucket*",
                                    "s3:GetObject*",
                                    "s3:List*",
                                    "s3:PutObject",
                                    "s3:PutObjectLegalHold",
                                    "s3:PutObjectRetention",
                                    "s3:PutObjectTagging",
                                    "s3:PutObjectVersionTagging"
                                  ],
                                  "Effect": "Allow",
                                  "Resource": [
                                    {
                                      "Fn::GetAtt": [
                                        "Capstone4PipelineArtifactsBucket5F833360",
                                        "Arn"
                                      ]
                                    },
                                    {
                                      "Fn::Join": [
                                        "",
                                        [
                                          {
                                            "Fn::GetAtt": [
                                              "Capstone4PipelineArtifactsBucket5F833360",
                                              "Arn"
                                            ]
                                          },
                                          "/*"
                                        ]
                                      ]
                                    }
                                  ]
                                },
                                {
                                  "Action": [
                                    "kms:Decrypt",
                                    "kms:DescribeKey",
                                    "kms:Encrypt",
                                    "kms:GenerateDataKey*",
                                    "kms:ReEncrypt*"
                                  ],
                                  "Effect": "Allow",
                                  "Resource": {
                                    "Fn::GetAtt": [
                                      "Capstone4PipelineArtifactsBucketEncryptionKey93347FCF",
                                      "Arn"
                                    ]
                                  }
                                }
                              ],
                              "Version": "2012-10-17"
                            },
                            "policyName": "CdkBuildProjectRoleDefaultPolicy3C7ECB00",
                            "roles": [
                              {
                                "Ref": "CdkBuildProjectRoleE0B6FEB0"
                              }
                            ]
                          }
                        },
                        "constructInfo": {
                          "fqn": "aws-cdk-lib.aws_iam.CfnPolicy",
                          "version": "2.100.0"
                        }
                      }
                    },
                    "constructInfo": {
                      "fqn": "aws-cdk-lib.aws_iam.Policy",
                      "version": "2.100.0"
                    }
                  }
                },
                "constructInfo": {
                  "fqn": "aws-cdk-lib.aws_iam.Role",
                  "version": "2.100.0"
                }
              },
              "Resource": {
                "id": "Resource",
                "path": "PipelineStack/CdkBuildProject/Resource",
                "attributes": {
                  "aws:cdk:cloudformation:type": "AWS::CodeBuild::Project",
                  "aws:cdk:cloudformation:props": {
                    "artifacts": {
                      "type": "CODEPIPELINE"
                    },
                    "cache": {
                      "type": "NO_CACHE"
                    },
                    "encryptionKey": {
                      "Fn::GetAtt": [
                        "Capstone4PipelineArtifactsBucketEncryptionKey93347FCF",
                        "Arn"
                      ]
                    },
                    "environment": {
                      "type": "LINUX_CONTAINER",
                      "image": "aws/codebuild/standard:7.0",
                      "imagePullCredentialsType": "CODEBUILD",
                      "privilegedMode": false,
                      "computeType": "BUILD_GENERAL1_SMALL"
                    },
                    "name": "capstone4-cdk-build",
                    "serviceRole": {
                      "Fn::GetAtt": [
                        "CdkBuildProjectRoleE0B6FEB0",
                        "Arn"
                      ]
                    },
                    "source": {
                      "type": "CODEPIPELINE",
                      "buildSpec": "{\n  \"version\": \"0.2\",\n  \"phases\": {\n    \"install\": {\n      \"runtime-versions\": {\n        \"nodejs\": \"18\"\n      },\n      \"commands\": [\n        \"echo Installing dependencies...\",\n        \"npm ci\"\n      ]\n    },\n    \"build\": {\n      \"commands\": [\n        \"echo Build started on `date`\",\n        \"npm run build\",\n        \"npx cdk synth\"\n      ]\n    },\n    \"post_build\": {\n      \"commands\": [\n        \"echo Deploying CDK stacks...\",\n        \"npx cdk deploy WorkflowStack --require-approval never\"\n      ]\n    }\n  },\n  \"artifacts\": {\n    \"base-directory\": \"cdk.out\",\n    \"files\": [\n      \"**/*\"\n    ]\n  }\n}"
                    }
                  }
                },
                "constructInfo": {
                  "fqn": "aws-cdk-lib.aws_codebuild.CfnProject",
                  "version": "2.100.0"
                }
              }
            },
            "constructInfo": {
              "fqn": "aws-cdk-lib.aws_codebuild.PipelineProject",
              "version": "2.100.0"
            }
          },
          "Capstone4Pipeline": {
            "id": "Capstone4Pipeline",
            "path": "PipelineStack/Capstone4Pipeline",
            "children": {
              "ArtifactsBucketEncryptionKey": {
                "id": "ArtifactsBucketEncryptionKey",
                "path": "PipelineStack/Capstone4Pipeline/ArtifactsBucketEncryptionKey",
                "children": {
                  "Resource": {
                    "id": "Resource",
                    "path": "PipelineStack/Capstone4Pipeline/ArtifactsBucketEncryptionKey/Resource",
                    "attributes": {
                      "aws:cdk:cloudformation:type": "AWS::KMS::Key",
                      "aws:cdk:cloudformation:props": {
                        "keyPolicy": {
                          "Statement": [
                            {
                              "Action": "kms:*",
                              "Effect": "Allow",
                              "Principal": {
                                "AWS": {
                                  "Fn::Join": [
                                    "",
                                    [
                                      "arn:",
                                      {
                                        "Ref": "AWS::Partition"
                                      },
                                      ":iam::132831332261:root"
                                    ]
                                  ]
                                }
                              },
                              "Resource": "*"
                            }
                          ],
                          "Version": "2012-10-17"
                        }
                      }
                    },
                    "constructInfo": {
                      "fqn": "aws-cdk-lib.aws_kms.CfnKey",
                      "version": "2.100.0"
                    }
                  }
                },
                "constructInfo": {
                  "fqn": "aws-cdk-lib.aws_kms.Key",
                  "version": "2.100.0"
                }
              },
              "ArtifactsBucketEncryptionKeyAlias": {
                "id": "ArtifactsBucketEncryptionKeyAlias",
                "path": "PipelineStack/Capstone4Pipeline/ArtifactsBucketEncryptionKeyAlias",
                "children": {
                  "Resource": {
                    "id": "Resource",
                    "path": "PipelineStack/Capstone4Pipeline/ArtifactsBucketEncryptionKeyAlias/Resource",
                    "attributes": {
                      "aws:cdk:cloudformation:type": "AWS::KMS::Alias",
                      "aws:cdk:cloudformation:props": {
                        "aliasName": "alias/codepipeline-pipelinestackcapstone4pipeline82f48d1c",
                        "targetKeyId": {
                          "Fn::GetAtt": [
                            "Capstone4PipelineArtifactsBucketEncryptionKey93347FCF",
                            "Arn"
                          ]
                        }
                      }
                    },
                    "constructInfo": {
                      "fqn": "aws-cdk-lib.aws_kms.CfnAlias",
                      "version": "2.100.0"
                    }
                  }
                },
                "constructInfo": {
                  "fqn": "aws-cdk-lib.aws_kms.Alias",
                  "version": "2.100.0"
                }
              },
              "ArtifactsBucket": {
                "id": "ArtifactsBucket",
                "path": "PipelineStack/Capstone4Pipeline/ArtifactsBucket",
                "children": {
                  "Resource": {
                    "id": "Resource",
                    "path": "PipelineStack/Capstone4Pipeline/ArtifactsBucket/Resource",
                    "attributes": {
                      "aws:cdk:cloudformation:type": "AWS::S3::Bucket",
                      "aws:cdk:cloudformation:props": {
                        "bucketEncryption": {
                          "serverSideEncryptionConfiguration": [
                            {
                              "serverSideEncryptionByDefault": {
                                "sseAlgorithm": "aws:kms",
                                "kmsMasterKeyId": {
                                  "Fn::GetAtt": [
                                    "Capstone4PipelineArtifactsBucketEncryptionKey93347FCF",
                                    "Arn"
                                  ]
                                }
                              }
                            }
                          ]
                        },
                        "publicAccessBlockConfiguration": {
                          "blockPublicAcls": true,
                          "blockPublicPolicy": true,
                          "ignorePublicAcls": true,
                          "restrictPublicBuckets": true
                        }
                      }
                    },
                    "constructInfo": {
                      "fqn": "aws-cdk-lib.aws_s3.CfnBucket",
                      "version": "2.100.0"
                    }
                  },
                  "Policy": {
                    "id": "Policy",
                    "path": "PipelineStack/Capstone4Pipeline/ArtifactsBucket/Policy",
                    "children": {
                      "Resource": {
                        "id": "Resource",
                        "path": "PipelineStack/Capstone4Pipeline/ArtifactsBucket/Policy/Resource",
                        "attributes": {
                          "aws:cdk:cloudformation:type": "AWS::S3::BucketPolicy",
                          "aws:cdk:cloudformation:props": {
                            "bucket": {
                              "Ref": "Capstone4PipelineArtifactsBucket5F833360"
                            },
                            "policyDocument": {
                              "Statement": [
                                {
                                  "Action": "s3:*",
                                  "Condition": {
                                    "Bool": {
                                      "aws:SecureTransport": "false"
                                    }
                                  },
                                  "Effect": "Deny",
                                  "Principal": {
                                    "AWS": "*"
                                  },
                                  "Resource": [
                                    {
                                      "Fn::GetAtt": [
                                        "Capstone4PipelineArtifactsBucket5F833360",
                                        "Arn"
                                      ]
                                    },
                                    {
                                      "Fn::Join": [
                                        "",
                                        [
                                          {
                                            "Fn::GetAtt": [
                                              "Capstone4PipelineArtifactsBucket5F833360",
                                              "Arn"
                                            ]
                                          },
                                          "/*"
                                        ]
                                      ]
                                    }
                                  ]
                                }
                              ],
                              "Version": "2012-10-17"
                            }
                          }
                        },
                        "constructInfo": {
                          "fqn": "aws-cdk-lib.aws_s3.CfnBucketPolicy",
                          "version": "2.100.0"
                        }
                      }
                    },
                    "constructInfo": {
                      "fqn": "aws-cdk-lib.aws_s3.BucketPolicy",
                      "version": "2.100.0"
                    }
                  }
                },
                "constructInfo": {
                  "fqn": "aws-cdk-lib.aws_s3.Bucket",
                  "version": "2.100.0"
                }
              },
              "Role": {
                "id": "Role",
                "path": "PipelineStack/Capstone4Pipeline/Role",
                "children": {
                  "ImportRole": {
                    "id": "ImportRole",
                    "path": "PipelineStack/Capstone4Pipeline/Role/ImportRole",
                    "constructInfo": {
                      "fqn": "aws-cdk-lib.Resource",
                      "version": "2.100.0"
                    }
                  },
                  "Resource": {
                    "id": "Resource",
                    "path": "PipelineStack/Capstone4Pipeline/Role/Resource",
                    "attributes": {
                      "aws:cdk:cloudformation:type": "AWS::IAM::Role",
                      "aws:cdk:cloudformation:props": {
                        "assumeRolePolicyDocument": {
                          "Statement": [
                            {
                              "Action": "sts:AssumeRole",
                              "Effect": "Allow",
                              "Principal": {
                                "Service": "codepipeline.amazonaws.com"
                              }
                            }
                          ],
                          "Version": "2012-10-17"
                        }
                      }
                    },
                    "constructInfo": {
                      "fqn": "aws-cdk-lib.aws_iam.CfnRole",
                      "version": "2.100.0"
                    }
                  },
                  "DefaultPolicy": {
                    "id": "DefaultPolicy",
                    "path": "PipelineStack/Capstone4Pipeline/Role/DefaultPolicy",
                    "children": {
                      "Resource": {
                        "id": "Resource",
                        "path": "PipelineStack/Capstone4Pipeline/Role/DefaultPolicy/Resource",
                        "attributes": {
                          "aws:cdk:cloudformation:type": "AWS::IAM::Policy",
                          "aws:cdk:cloudformation:props": {
                            "policyDocument": {
                              "Statement": [
                                {
                                  "Action": [
                                    "s3:Abort*",
                                    "s3:DeleteObject*",
                                    "s3:GetBucket*",
                                    "s3:GetObject*",
                                    "s3:List*",
                                    "s3:PutObject",
                                    "s3:PutObjectLegalHold",
                                    "s3:PutObjectRetention",
                                    "s3:PutObjectTagging",
                                    "s3:PutObjectVersionTagging"
                                  ],
                                  "Effect": "Allow",
                                  "Resource": [
                                    {
                                      "Fn::GetAtt": [
                                        "Capstone4PipelineArtifactsBucket5F833360",
                                        "Arn"
                                      ]
                                    },
                                    {
                                      "Fn::Join": [
                                        "",
                                        [
                                          {
                                            "Fn::GetAtt": [
                                              "Capstone4PipelineArtifactsBucket5F833360",
                                              "Arn"
                                            ]
                                          },
                                          "/*"
                                        ]
                                      ]
                                    }
                                  ]
                                },
                                {
                                  "Action": [
                                    "kms:Decrypt",
                                    "kms:DescribeKey",
                                    "kms:Encrypt",
                                    "kms:GenerateDataKey*",
                                    "kms:ReEncrypt*"
                                  ],
                                  "Effect": "Allow",
                                  "Resource": {
                                    "Fn::GetAtt": [
                                      "Capstone4PipelineArtifactsBucketEncryptionKey93347FCF",
                                      "Arn"
                                    ]
                                  }
                                },
                                {
                                  "Action": "sts:AssumeRole",
                                  "Effect": "Allow",
                                  "Resource": {
                                    "Fn::GetAtt": [
                                      "Capstone4PipelineBuildAndDeployCDKBuildDeployCodePipelineActionRole4B426F4B",
                                      "Arn"
                                    ]
                                  }
                                }
                              ],
                              "Version": "2012-10-17"
                            },
                            "policyName": "Capstone4PipelineRoleDefaultPolicyE080AF0B",
                            "roles": [
                              {
                                "Ref": "Capstone4PipelineRole9D8648B3"
                              }
                            ]
                          }
                        },
                        "constructInfo": {
                          "fqn": "aws-cdk-lib.aws_iam.CfnPolicy",
                          "version": "2.100.0"
                        }
                      }
                    },
                    "constructInfo": {
                      "fqn": "aws-cdk-lib.aws_iam.Policy",
                      "version": "2.100.0"
                    }
                  }
                },
                "constructInfo": {
                  "fqn": "aws-cdk-lib.aws_iam.Role",
                  "version": "2.100.0"
                }
              },
              "Resource": {
                "id": "Resource",
                "path": "PipelineStack/Capstone4Pipeline/Resource",
                "attributes": {
                  "aws:cdk:cloudformation:type": "AWS::CodePipeline::Pipeline",
                  "aws:cdk:cloudformation:props": {
                    "artifactStore": {
                      "type": "S3",
                      "location": {
                        "Ref": "Capstone4PipelineArtifactsBucket5F833360"
                      },
                      "encryptionKey": {
                        "type": "KMS",
                        "id": {
                          "Fn::GetAtt": [
                            "Capstone4PipelineArtifactsBucketEncryptionKey93347FCF",
                            "Arn"
                          ]
                        }
                      }
                    },
                    "name": "capstone4-iac-pipeline",
                    "roleArn": {
                      "Fn::GetAtt": [
                        "Capstone4PipelineRole9D8648B3",
                        "Arn"
                      ]
                    },
                    "stages": [
                      {
                        "name": "Source",
                        "actions": [
                          {
                            "name": "GitHub_Source",
                            "outputArtifacts": [
                              {
                                "name": "SourceArtifact"
                              }
                            ],
                            "actionTypeId": {
                              "category": "Source",
                              "version": "1",
                              "owner": "ThirdParty",
                              "provider": "GitHub"
                            },
                            "configuration": {
                              "Owner": "Evanoken",
                              "Repo": "capstone4",
                              "Branch": "main",
                              "OAuthToken": "{{resolve:secretsmanager:github-token:SecretString:::}}",
                              "PollForSourceChanges": false
                            },
                            "runOrder": 1
                          }
                        ]
                      },
                      {
                        "name": "BuildAndDeploy",
                        "actions": [
                          {
                            "name": "CDK_Build_Deploy",
                            "inputArtifacts": [
                              {
                                "name": "SourceArtifact"
                              }
                            ],
                            "outputArtifacts": [
                              {
                                "name": "BuildArtifact"
                              }
                            ],
                            "actionTypeId": {
                              "category": "Build",
                              "version": "1",
                              "owner": "AWS",
                              "provider": "CodeBuild"
                            },
                            "configuration": {
                              "ProjectName": {
                                "Ref": "CdkBuildProject9382C38D"
                              }
                            },
                            "runOrder": 1,
                            "roleArn": {
                              "Fn::GetAtt": [
                                "Capstone4PipelineBuildAndDeployCDKBuildDeployCodePipelineActionRole4B426F4B",
                                "Arn"
                              ]
                            }
                          }
                        ]
                      }
                    ]
                  }
                },
                "constructInfo": {
                  "fqn": "aws-cdk-lib.aws_codepipeline.CfnPipeline",
                  "version": "2.100.0"
                }
              },
              "Source": {
                "id": "Source",
                "path": "PipelineStack/Capstone4Pipeline/Source",
                "children": {
                  "GitHub_Source": {
                    "id": "GitHub_Source",
                    "path": "PipelineStack/Capstone4Pipeline/Source/GitHub_Source",
                    "children": {
                      "WebhookResource": {
                        "id": "WebhookResource",
                        "path": "PipelineStack/Capstone4Pipeline/Source/GitHub_Source/WebhookResource",
                        "attributes": {
                          "aws:cdk:cloudformation:type": "AWS::CodePipeline::Webhook",
                          "aws:cdk:cloudformation:props": {
                            "authentication": "GITHUB_HMAC",
                            "authenticationConfiguration": {
                              "secretToken": "{{resolve:secretsmanager:github-token:SecretString:::}}"
                            },
                            "filters": [
                              {
                                "jsonPath": "$.ref",
                                "matchEquals": "refs/heads/{Branch}"
                              }
                            ],
                            "registerWithThirdParty": true,
                            "targetAction": "GitHub_Source",
                            "targetPipeline": {
                              "Ref": "Capstone4Pipeline58C8DB69"
                            },
                            "targetPipelineVersion": 1
                          }
                        },
                        "constructInfo": {
                          "fqn": "aws-cdk-lib.aws_codepipeline.CfnWebhook",
                          "version": "2.100.0"
                        }
                      }
                    },
                    "constructInfo": {
                      "fqn": "constructs.Construct",
                      "version": "10.6.0"
                    }
                  }
                },
                "constructInfo": {
                  "fqn": "constructs.Construct",
                  "version": "10.6.0"
                }
              },
              "BuildAndDeploy": {
                "id": "BuildAndDeploy",
                "path": "PipelineStack/Capstone4Pipeline/BuildAndDeploy",
                "children": {
                  "CDK_Build_Deploy": {
                    "id": "CDK_Build_Deploy",
                    "path": "PipelineStack/Capstone4Pipeline/BuildAndDeploy/CDK_Build_Deploy",
                    "children": {
                      "CodePipelineActionRole": {
                        "id": "CodePipelineActionRole",
                        "path": "PipelineStack/Capstone4Pipeline/BuildAndDeploy/CDK_Build_Deploy/CodePipelineActionRole",
                        "children": {
                          "ImportCodePipelineActionRole": {
                            "id": "ImportCodePipelineActionRole",
                            "path": "PipelineStack/Capstone4Pipeline/BuildAndDeploy/CDK_Build_Deploy/CodePipelineActionRole/ImportCodePipelineActionRole",
                            "constructInfo": {
                              "fqn": "aws-cdk-lib.Resource",
                              "version": "2.100.0"
                            }
                          },
                          "Resource": {
                            "id": "Resource",
                            "path": "PipelineStack/Capstone4Pipeline/BuildAndDeploy/CDK_Build_Deploy/CodePipelineActionRole/Resource",
                            "attributes": {
                              "aws:cdk:cloudformation:type": "AWS::IAM::Role",
                              "aws:cdk:cloudformation:props": {
                                "assumeRolePolicyDocument": {
                                  "Statement": [
                                    {
                                      "Action": "sts:AssumeRole",
                                      "Effect": "Allow",
                                      "Principal": {
                                        "AWS": {
                                          "Fn::Join": [
                                            "",
                                            [
                                              "arn:",
                                              {
                                                "Ref": "AWS::Partition"
                                              },
                                              ":iam::132831332261:root"
                                            ]
                                          ]
                                        }
                                      }
                                    }
                                  ],
                                  "Version": "2012-10-17"
                                }
                              }
                            },
                            "constructInfo": {
                              "fqn": "aws-cdk-lib.aws_iam.CfnRole",
                              "version": "2.100.0"
                            }
                          },
                          "DefaultPolicy": {
                            "id": "DefaultPolicy",
                            "path": "PipelineStack/Capstone4Pipeline/BuildAndDeploy/CDK_Build_Deploy/CodePipelineActionRole/DefaultPolicy",
                            "children": {
                              "Resource": {
                                "id": "Resource",
                                "path": "PipelineStack/Capstone4Pipeline/BuildAndDeploy/CDK_Build_Deploy/CodePipelineActionRole/DefaultPolicy/Resource",
                                "attributes": {
                                  "aws:cdk:cloudformation:type": "AWS::IAM::Policy",
                                  "aws:cdk:cloudformation:props": {
                                    "policyDocument": {
                                      "Statement": [
                                        {
                                          "Action": [
                                            "codebuild:BatchGetBuilds",
                                            "codebuild:StartBuild",
                                            "codebuild:StopBuild"
                                          ],
                                          "Effect": "Allow",
                                          "Resource": {
                                            "Fn::GetAtt": [
                                              "CdkBuildProject9382C38D",
                                              "Arn"
                                            ]
                                          }
                                        }
                                      ],
                                      "Version": "2012-10-17"
                                    },
                                    "policyName": "Capstone4PipelineBuildAndDeployCDKBuildDeployCodePipelineActionRoleDefaultPolicyE6EA7725",
                                    "roles": [
                                      {
                                        "Ref": "Capstone4PipelineBuildAndDeployCDKBuildDeployCodePipelineActionRole4B426F4B"
                                      }
                                    ]
                                  }
                                },
                                "constructInfo": {
                                  "fqn": "aws-cdk-lib.aws_iam.CfnPolicy",
                                  "version": "2.100.0"
                                }
                              }
                            },
                            "constructInfo": {
                              "fqn": "aws-cdk-lib.aws_iam.Policy",
                              "version": "2.100.0"
                            }
                          }
                        },
                        "constructInfo": {
                          "fqn": "aws-cdk-lib.aws_iam.Role",
                          "version": "2.100.0"
                        }
                      }
                    },
                    "constructInfo": {
                      "fqn": "constructs.Construct",
                      "version": "10.6.0"
                    }
                  }
                },
                "constructInfo": {
                  "fqn": "constructs.Construct",
                  "version": "10.6.0"
                }
              }
            },
            "constructInfo": {
              "fqn": "aws-cdk-lib.aws_codepipeline.Pipeline",
              "version": "2.100.0"
            }
          },
          "CDKMetadata": {
            "id": "CDKMetadata",
            "path": "PipelineStack/CDKMetadata",
            "children": {
              "Default": {
                "id": "Default",
                "path": "PipelineStack/CDKMetadata/Default",
                "constructInfo": {
                  "fqn": "aws-cdk-lib.CfnResource",
                  "version": "2.100.0"
                }
              }
            },
            "constructInfo": {
              "fqn": "constructs.Construct",
              "version": "10.6.0"
            }
          },
          "BootstrapVersion": {
            "id": "BootstrapVersion",
            "path": "PipelineStack/BootstrapVersion",
            "constructInfo": {
              "fqn": "aws-cdk-lib.CfnParameter",
              "version": "2.100.0"
            }
          },
          "CheckBootstrapVersion": {
            "id": "CheckBootstrapVersion",
            "path": "PipelineStack/CheckBootstrapVersion",
            "constructInfo": {
              "fqn": "aws-cdk-lib.CfnRule",
              "version": "2.100.0"
            }
          }
        },
        "constructInfo": {
          "fqn": "aws-cdk-lib.Stack",
          "version": "2.100.0"
        }
      },
      "Tree": {
        "id": "Tree",
        "path": "Tree",
        "constructInfo": {
          "fqn": "constructs.Construct",
          "version": "10.6.0"
        }
      }
    },
    "constructInfo": {
      "fqn": "aws-cdk-lib.App",
      "version": "2.100.0"
    }
  }
}